{
    "name": "Global Information",
    "numberOfRequests": {
        "total": 6551,
        "ok": 6068,
        "ko": 483
    },
    "minResponseTime": {
        "total": 257,
        "ok": 257,
        "ko": 7270
    },
    "maxResponseTime": {
        "total": 49572,
        "ok": 49572,
        "ko": 28400
    },
    "meanResponseTime": {
        "total": 7289,
        "ok": 6979,
        "ko": 11190
    },
    "standardDeviation": {
        "total": 5961,
        "ok": 6054,
        "ko": 2269
    },
    "percentiles1": {
        "total": 6233,
        "ok": 5565,
        "ko": 10845
    },
    "percentiles2": {
        "total": 10762,
        "ok": 10214,
        "ko": 11443
    },
    "percentiles3": {
        "total": 17755,
        "ok": 18036,
        "ko": 12045
    },
    "percentiles4": {
        "total": 26637,
        "ok": 26631,
        "ko": 25585
    },
    "group1": {
    "name": "t < 800 ms",
    "count": 659,
    "percentage": 10
},
    "group2": {
    "name": "800 ms < t < 1200 ms",
    "count": 377,
    "percentage": 6
},
    "group3": {
    "name": "t > 1200 ms",
    "count": 5032,
    "percentage": 77
},
    "group4": {
    "name": "failed",
    "count": 483,
    "percentage": 7
},
    "meanNumberOfRequestsPerSecond": {
        "total": 125.98076923076923,
        "ok": 116.6923076923077,
        "ko": 9.288461538461538
    }
}